{
  "layouts": {
    "Sound-Voices-Layout": {
      "Selector": {
        "UIFocus": "Sound",
        "UIMode": "Select",
        "UIDetail": "Voices"
      },
      "Controls": {
        "Header": {
          "Class": "InvertedLabel",
          "Position": "0, 0",
          "Events": "EditBufferTypeText => Text[Text]"
        },
        "ButtonA": {
          "Class": "Button",
          "Position": "BUTTON_A",
          "Events": "SelectVGButtonText => Text[Text]"
        },
        "ButtonB": {
          "Class": "Button",
          "Position": "BUTTON_B",
          "Init": {
            "Text[Text]": "Mono .."
          }
        },
        "ButtonC": {
          "Class": "Button",
          "Position": "BUTTON_C",
          "Init": {
            "Text[Text]": "Unison .."
          }
        },
        "ButtonD": {
          "Class": "Button",
          "Position": "BUTTON_D"
        },
        "Mono": {
          "Class": "Label",
          "Position": "66, 0",
          "Init": {
            "Text[Text]": "Mono"
          }
        },
        "Mono-Group": {
          "Class": "Group-Control-Border",
          "Position": "10, 15"
        },
        "Legato": {
          "Class": "ParameterPair",
          "Position": "12, 16",
          "Init": {
            "Value[Text]": "66%",
            "Label[Text]": "Legato"
          }
        },
        "Prio": {
          "Class": "ParameterPair",
          "Position": "12, 26",
          "Init": {
            "Value[Text]": "Highest",
            "Label[Text]": "Priority"
          }
        },
        "Glide": {
          "Class": "ParameterPair",
          "Position": "12, 36",
          "Init": {
            "Value[Text]": "Yes",
            "Label[Text]": "Glide"
          }
        },
        "Voices": {
          "Class": "ParameterPair",
          "Position": "127, 2",
          "Init": {
            "Value[Text]": "1",
            "Label[Text]": "Voices"
          }
        },
        "Unison-Group": {
          "Class": "Group-Control-Border",
          "Position": "133, 15"
        },
        "Detune": {
          "Class": "ParameterPair",
          "Position": "132, 16",
          "Init": {
            "Value[Text]": "2.88%",
            "Label[Text]": "Detune"
          }
        },
        "Phase": {
          "Class": "ParameterPair",
          "Position": "132, 26",
          "Init": {
            "Value[Text]": "No",
            "Label[Text]": "Phase"
          }
        },
        "Pan": {
          "Class": "ParameterPair",
          "Position": "132, 36",
          "Init": {
            "Value[Text]": "-50%",
            "Label[Text]": "Pan"
          }
        }
      },
      "EventSinks": {
        "BUTTON_A": "ToggleVoiceGroup",
        "BUTTON_B": "OpenMonoParameterScreen",
        "BUTTON_C": "OpenUnisonParameterScreen"
      }
    }
  }
}